[
    {
       "name": "Redmi Note 8 Pro",
       "brand": "Xiaomi",
       "codename": "begonia",
       "supported_versions": [
          {
             "version_code": "thundra",
             "stable": true,
             "deprecated": false
          }
       ],
       "repositories": [
          "device_xiaomi_begonia",
          "vendor_xiaomi_begonia",
          "vendor_xiaomi_begonia-ims",
          "vendor_xiaomi_begonia-firmware",
          "kernel_xiaomi_mt6785",
          "hardware_mediatek",
          "device_mediatek_sepolicy-begonia"
       ]
    }
]